ZikongliJingdianTaozhuangX3/README.md
ZikongliJingdianTaozhuangX3/__init__.py
ZikongliJingdianTaozhuangX3/__main__.py
ZikongliJingdianTaozhuangX3/file.epub
ZikongliJingdianTaozhuangX3/index.html
ZikongliJingdianTaozhuangX3/css/__init__.py
ZikongliJingdianTaozhuangX3/css/annotations.css
ZikongliJingdianTaozhuangX3/css/main.css
ZikongliJingdianTaozhuangX3/css/normalize.css
ZikongliJingdianTaozhuangX3/css/popup.css
ZikongliJingdianTaozhuangX3/font/__init__.py
ZikongliJingdianTaozhuangX3/font/fontello.eot
ZikongliJingdianTaozhuangX3/font/fontello.svg
ZikongliJingdianTaozhuangX3/font/fontello.ttf
ZikongliJingdianTaozhuangX3/font/fontello.woff
ZikongliJingdianTaozhuangX3/img/__init__.py
ZikongliJingdianTaozhuangX3/img/annotator-glyph-sprite.png
ZikongliJingdianTaozhuangX3/img/annotator-icon-sprite.png
ZikongliJingdianTaozhuangX3/img/apple-touch-icon.png
ZikongliJingdianTaozhuangX3/img/cancelfullscreen.png
ZikongliJingdianTaozhuangX3/img/close.png
ZikongliJingdianTaozhuangX3/img/fullscreen.png
ZikongliJingdianTaozhuangX3/img/loader.gif
ZikongliJingdianTaozhuangX3/img/menu-icon.png
ZikongliJingdianTaozhuangX3/img/save.png
ZikongliJingdianTaozhuangX3/img/saved.png
ZikongliJingdianTaozhuangX3/img/settings-s.png
ZikongliJingdianTaozhuangX3/img/settings.png
ZikongliJingdianTaozhuangX3/img/star.png
ZikongliJingdianTaozhuangX3/js/__init__.py
ZikongliJingdianTaozhuangX3/js/epub.js
ZikongliJingdianTaozhuangX3/js/epub.min.js
ZikongliJingdianTaozhuangX3/js/epub.min.map
ZikongliJingdianTaozhuangX3/js/hooks.min.js
ZikongliJingdianTaozhuangX3/js/hooks.min.map
ZikongliJingdianTaozhuangX3/js/reader.js
ZikongliJingdianTaozhuangX3/js/reader.js.map
ZikongliJingdianTaozhuangX3/js/reader.min.js
ZikongliJingdianTaozhuangX3/js/reader.min.map
ZikongliJingdianTaozhuangX3/js/hooks/__init__.py
ZikongliJingdianTaozhuangX3/js/hooks/extensions/__init__.py
ZikongliJingdianTaozhuangX3/js/hooks/extensions/highlight.js
ZikongliJingdianTaozhuangX3/js/libs/__init__.py
zikongli_jingdian_taozhuang_x3-2022.10.15.0.dist-info/METADATA
zikongli_jingdian_taozhuang_x3-2022.10.15.0.dist-info/WHEEL
zikongli_jingdian_taozhuang_x3-2022.10.15.0.dist-info/entry_points.txt
zikongli_jingdian_taozhuang_x3-2022.10.15.0.dist-info/top_level.txt
zikongli_jingdian_taozhuang_x3-2022.10.15.0.dist-info/RECORD
